Workbook

Sheet 0_前提条件
B2: FP顧客ヒアリング兼シミュレーター(試作版) — 前提条件・取扱説明
B4: ■ 本ツールの目的
B5: 利用者 | C5: ファイナンシャルプランナー(FP)
B6: 用途 | C6: 顧客ヒアリング → 所得税・住民税・国保・iDeCo・退職金・ふるさと納税・NISA取り崩しの試算を一括で行う
B7: 対象顧客 | C7: 自営業(第1号被保険者)/会社員(第2号被保険者) 両対応
B8: 入力方法 | C8: 「1_ヒアリングシート」の青文字セル(黄色背景=要確認)に入力するだけで全シートが自動再計算
B10: ■ 試作の前提条件(2026年度ベース)
B11: 税制基準年 | C11: 2026年度(令和8年度)を想定
B12: 所得税 | C12: 国税庁の超過累進税率(5%〜45%)を使用。復興特別所得税2.1%を上乗せ
B13: 住民税 | C13: 一律10%(都道府県民税4%+市町村民税6%)+均等割5,000円。東京都標準を採用
B14: 基礎控除 | C14: 所得税48万円/住民税43万円(合計所得2,400万円以下を想定)
B15: 給与所得控除 | C15: 2020年改正後の式を使用(会社員のみ)
B16: 青色申告特別控除 | C16: 65万円(電子申告前提・自営業のみ)
B17: 社会保険料(自営業) | C17: 国民年金 月額17,510円×12/国民健康保険は東京都標準率で簡易計算
B18: 社会保険料(会社員) | C18: 額面の約15%で簡易計算(健保・厚生年金・雇用保険合算)
B19: iDeCo上限 | C19: 自営業68,000円/月、会社員23,000円/月(企業年金なし想定)
B20: 退職所得控除 | C20: 勤続20年まで40万円/年、20年超は70万円/年
B21: ふるさと納税 | C21: 総務省の簡易計算式 (住民税所得割×20% / (90% - 所得税率×1.021)) + 2,000円
B22: NISA | C22: 新NISA(2024〜) 年間360万円、生涯1,800万円。運用益非課税
B24: ■ 可変箇所(FPさんが顧客ごとに変更する項目)
B25: 青文字セル | C25: 全て上書き可能。黄色背景セルは特に「必ず聞き取る項目」
B26: 運用利回り | C26: iDeCo・NISAともに「2_詳細設定」で可変(デフォルト3%)
B27: 退職金見込額 | C27: 顧客ヒアリングで取得
B28: 掛金額 | C28: 顧客現在の掛金 → 上限額まで増額した場合の比較を自動表示
B30: ■ 固定箇所(本試作では未対応)
B31: ふるさと納税 | C31: 正確な上限は所得控除の組合せで変動。本ツールは概算
B32: 住民税 | C32: 自治体ごとの均等割超過税率は未対応(東京都標準のみ)
B33: 国保 | C33: 自治体ごとの料率差は未対応
B34: iDeCo | C34: 受取時の退職所得控除との重複期間ルール(5年・19年ルール)は簡易表示
B35: 配偶者・扶養控除 | C35: 人数のみ反映。年齢区分(特定扶養等)は未対応
B37: ■ 凡例
B38: 青文字 | C38: ヒアリング入力欄(上書き可)
B39: 黒文字 | C39: 自動計算
B40: 緑文字 | C40: 他シートからの参照
B41: 黄色背景 | C41: 特に重要な入力項目

Sheet 1_ヒアリングシート
B2: 顧客ヒアリングシート(青セル/黄セルに入力)
B4: ■ 基本情報
B5: 顧客氏名 | C5: 山田 太郎 | D5: ヒアリング日 | E5: 46119
B6: 生年月日 | C6: 29356 | D6: 現在年齢(自動) | E6: =DATEDIF(C6,E5,"Y") -> 45
B7: 職業区分 | C7: 自営業 | D7: (自営業 or 会社員)
B8: 居住自治体 | C8: 東京都 | D8: 配偶者の有無 | E8: あり
B9: 扶養親族の人数 | C9: 1 | D9: (うち16歳未満) | E9: 0
B11: ■ 収入(年額)
B12: 事業収入(売上) | C12: 8000000 | D12: 事業経費 | E12: 2000000
B13: 給与収入(額面) | C13: 0 | D13: その他所得 | E13: 0
B15: ■ 社会保険・所得控除(把握分)
B16: 社会保険料(年額・実額) | C16: 0 | D16: (0なら自動推計)
B17: 生命保険料控除 | C17: 40000 | D17: 地震保険料控除 | E17: 0
B18: 医療費控除(見込) | C18: 0 | D18: 小規模企業共済掛金 | E18: 0
B20: ■ iDeCo
B21: 現在のiDeCo月額掛金 | C21: 20000 | D21: 拠出開始年齢 | E21: 40
B22: 受取予定年齢 | C22: 65 | D22: 想定運用利回り | E22: 0.03
B24: ■ 退職金(会社員 or 小規模企業共済)
B25: 退職金見込額 | C25: 15000000 | D25: 勤続年数 | E25: 25
B27: ■ NISA
B28: 現在のNISA残高 | C28: 3000000 | D28: 毎月積立額 | E28: 30000
B29: 取り崩し開始年齢 | C29: 65 | D29: 取り崩し期間(年) | E29: 25

Sheet 2_所得税住民税
B2: 所得税・住民税・社会保険料 自動計算
B4: 項目 | C4: 金額 | D4: 計算根拠
B5: 事業収入 | C5: ='1_ヒアリングシート'!C12 -> 8000000 | D5: ヒアリング入力
B6: 事業経費 | C6: ='1_ヒアリングシート'!E12 -> 2000000 | D6: ヒアリング入力
B7: 青色申告特別控除 | C7: =IF('1_ヒアリングシート'!C7="自営業",650000,0) -> 650000 | D7: 電子申告で65万円(自営業のみ)
B8: 事業所得 | C8: =MAX(0,C5-C6-C7) -> 5350000 | D8: 売上 − 経費 − 青色申告控除
B9: 給与収入 | C9: ='1_ヒアリングシート'!C13 -> 0
B10: 給与所得控除 | C10: =IF(C9<=1625000,550000,IF(C9<=1800000,C9*0.4-100000,IF(C9<=3600000,C9*0.3+80000,IF(C9<=6600000,C9*0.2+440000,IF(C9<=8500000,C9*0.1+1100000,1950000))))) -> 550000 | D10: 2020年改正後の速算表
B11: 給与所得 | C11: =MAX(0,C9-C10) -> 0
B12: 合計所得金額 | C12: =C8+C11+'1_ヒアリングシート'!E13 -> 5350000
B14: ■ 社会保険料
B15: 国民年金(自営業) | C15: =IF('1_ヒアリングシート'!C7="自営業",17510*12,0) -> 210120 | D15: 月17,510円×12
B16: 国民健康保険(概算) | C16: =IF('1_ヒアリングシート'!C7="自営業",MIN(1020000,C12*0.1+50000),0) -> 585000 | D16: 東京都標準・所得割10%+均等割 簡易計算
B17: 厚生年金等(会社員) | C17: =IF('1_ヒアリングシート'!C7="会社員",C9*0.15,0) -> 0 | D17: 額面の約15%で簡易計算
B18: iDeCo掛金(全額所得控除) | C18: ='1_ヒアリングシート'!C21*12 -> 240000 | D18: iDeCo月額×12
B19: 社会保険料控除 合計 | C19: =IF('1_ヒアリングシート'!C16>0,'1_ヒアリングシート'!C16,C15+C16+C17)+C18 -> 1035120 | D19: ヒアリング実額>0ならそれを優先+iDeCo
B21: ■ 所得控除
B22: 基礎控除 | C22: =480000 -> 480000 | D22: 所得税(2,400万円以下)
B23: 配偶者控除 | C23: =IF('1_ヒアリングシート'!E8="あり",380000,0) -> 380000
B24: 扶養控除 | C24: =('1_ヒアリングシート'!C9-'1_ヒアリングシート'!E9)*380000 -> 380000 | D24: 16歳以上のみ・一般扶養38万円で簡易
B25: 生命保険料控除 | C25: ='1_ヒアリングシート'!C17 -> 40000
B26: 地震保険料控除 | C26: ='1_ヒアリングシート'!E17 -> 0
B27: 医療費控除 | C27: ='1_ヒアリングシート'!C18 -> 0
B28: 小規模企業共済等掛金 | C28: ='1_ヒアリングシート'!E18 -> 0
B29: 所得控除合計 | C29: =C19+C22+C23+C24+C25+C26+C27+C28 -> 2315120
B31: ■ 税額計算
B32: 課税所得 | C32: =MAX(0,C12-C29) -> 3034880
B33: 所得税(超過累進) | C33: =IF(C32<=1950000,C32*0.05,IF(C32<=3300000,C32*0.1-97500,IF(C32<=6950000,C32*0.2-427500,IF(C32<=9000000,C32*0.23-636000,IF(C32<=18000000,C32*0.33-1536000,IF(C32<=40000000,C32*0.4-2796000,C32*0.45-4796000)))))) -> 205988 | D33: 国税庁速算表
B34: 復興特別所得税 | C34: =ROUND(C33*0.021,0) -> 4326
B35: 住民税(所得割10%+均等割) | C35: =MAX(0,C12-(C29-50000))*0.1+5000 -> 313488 | D35: 基礎控除差5万円調整・東京都標準
B36: 税・社保 合計負担 | C36: =C33+C34+C35+C19 -> 1558922
B37: 手取り | C37: =C5+C9-C6-C36 -> 4441078

Sheet 3_iDeCo
B2: iDeCo 節税効果・将来資産シミュレーション
B4: 前提
B5: 現在の月額掛金 | C5: ='1_ヒアリングシート'!C21 -> 20000
B6: 上限月額(自営業68,000/会社員23,000) | C6: =IF('1_ヒアリングシート'!C7="自営業",68000,23000) -> 68000
B7: 拠出年数 | C7: ='1_ヒアリングシート'!C22-'1_ヒアリングシート'!E21 -> 25
B8: 想定利回り | C8: ='1_ヒアリングシート'!E22 -> 0.03
B9: 適用税率(所得税+住民税) | C9: =IF('2_所得税住民税'!C32<=1950000,0.15,IF('2_所得税住民税'!C32<=3300000,0.2,IF('2_所得税住民税'!C32<=6950000,0.3,IF('2_所得税住民税'!C32<=9000000,0.33,IF('2_所得税住民税'!C32<=18000000,0.43,IF('2_所得税住民税'!C32<=40000000,0.5,0.55)))))) -> 0.2 | D9: 課税所得から逆引き(住民税10%含む)
B11: ■ シナリオ比較
B12: シナリオ | C12: 月額掛金 | D12: 年間節税額 | E12: 拠出元本 | F12: 受取見込額(運用後)
B13: ① 現状(ヒアリング値) | C13: =C5 -> 20000 | D13: =C13*12*C9 -> 48000 | E13: =C13*12*C7 -> 6000000 | F13: =IF(C8=0,E13,C13*12*((1+C8)^C7-1)/C8) -> 8750223.4
B14: ② 上限まで増額 | C14: =C6 -> 68000 | D14: =C14*12*C9 -> 163200 | E14: =C14*12*C7 -> 20400000 | F14: =IF(C8=0,E14,C14*12*((1+C8)^C7-1)/C8) -> 29750760
B15: ③ 上限の半額 | C15: =C6/2 -> 34000 | D15: =C15*12*C9 -> 81600 | E15: =C15*12*C7 -> 10200000 | F15: =IF(C8=0,E15,C15*12*((1+C8)^C7-1)/C8) -> 14875380
B17: ■ ポイント
B18: ・年間節税額 = 月額×12×(所得税率+住民税10%)。掛金は全額が小規模企業共済等掛金控除
B19: ・受取時は退職所得控除(一時金)or 公的年金等控除(年金)。退職金との重複に注意(5年・19年ルール)

Sheet 4_退職金
B2: 退職金 一時金 vs 年金 受取比較
B4: 退職金見込額 | C4: ='1_ヒアリングシート'!C25 -> 15000000
B5: 勤続年数 | C5: ='1_ヒアリングシート'!E25 -> 25
B6: 退職所得控除 | C6: =IF(C5<=20,400000*C5,8000000+700000*(C5-20)) -> 11500000 | D6: 20年以下:40万×年/20年超:800万+70万×(年-20)
B7: 退職所得(課税対象) | C7: =MAX(0,(C4-C6)/2) -> 1750000 | D7: (退職金 − 控除)×1/2
B8: 一時金 所得税 | C8: =IF(C7<=1950000,C7*0.05,IF(C7<=3300000,C7*0.1-97500,IF(C7<=6950000,C7*0.2-427500,IF(C7<=9000000,C7*0.23-636000,IF(C7<=18000000,C7*0.33-1536000,IF(C7<=40000000,C7*0.4-2796000,C7*0.45-4796000)))))) -> 87500
B9: 一時金 住民税 | C9: =C7*0.1 -> 175000
B10: ■ 一時金受取・手取り | C10: =C4-C8-C9 -> 14737500
B12: ■ 年金受取(10年分割の場合)
B13: 年間受取額 | C13: =C4/10 -> 1500000
B14: 公的年金等控除(65歳以上・概算) | C14: =1100000 -> 1100000 | D14: 65歳以上・年金収入330万円未満を想定
B15: 課税年金所得 | C15: =MAX(0,C13-C14) -> 400000
B16: 年金課税(所得税+住民税 簡易15%) | C16: =C15*0.15 -> 60000 | D16: 簡易15%で試算(他所得との合算で変動)
B17: ■ 年金受取・10年合計手取り | C17: =C4-C16*10 -> 14400000

Sheet 5_ふるさと納税
B2: ふるさと納税 上限額(概算)
B4: 課税所得 | C4: ='2_所得税住民税'!C32 -> 3034880
B5: 住民税所得割 | C5: =C4*0.1 -> 303488 | D5: 課税所得×10%
B6: 所得税率 | C6: =IF(C4<=1950000,0.05,IF(C4<=3300000,0.1,IF(C4<=6950000,0.2,IF(C4<=9000000,0.23,IF(C4<=18000000,0.33,IF(C4<=40000000,0.4,0.45)))))) -> 0.1
B7: ふるさと納税 上限(概算) | C7: =ROUNDDOWN(C5*0.2/(0.9-C6*1.021)+2000,0) -> 78071 | D7: 総務省簡易式 (住民税所得割×20%)/(90% − 所得税率×1.021) + 2,000円

Sheet 6_NISA取崩し
B2: NISA 積立 → 取り崩しシミュレーション
B4: 現在残高 | C4: ='1_ヒアリングシート'!C28 -> 3000000
B5: 毎月積立額 | C5: ='1_ヒアリングシート'!E28 -> 30000
B6: 現在年齢 | C6: ='1_ヒアリングシート'!E6 -> 45
B7: 取り崩し開始年齢 | C7: ='1_ヒアリングシート'!C29 -> 65
B8: 取り崩し期間(年) | C8: ='1_ヒアリングシート'!E29 -> 25
B9: 想定運用利回り | C9: 0.03
B10: 積立年数 | C10: =MAX(0,C7-C6) -> 20
B11: 取り崩し開始時 残高見込 | C11: =C4*(1+C9)^C10 + IF(C9=0,C5*12*C10,C5*12*((1+C9)^C10-1)/C9) -> 15091669
B12: ■ シナリオA:均等取り崩し(毎年同額) | C12: =IF(C9=0,C11/C8,C11*C9/(1-(1+C9)^(-C8))) -> 866682.39 | D12: 年金現価方式
B13: ■ シナリオB:定率4%取り崩し(年額) | C13: =C11*0.04 -> 603666.74 | D13: Trinity Study等で参照される4%ルール

Sheet 7_サマリー
B2: 顧客提示用 サマリー
B4: 顧客名 | C4: ='1_ヒアリングシート'!C5 -> 山田 太郎
B5: 年齢 | C5: ='1_ヒアリングシート'!E6 -> 45
B6: 職業 | C6: ='1_ヒアリングシート'!C7 -> 自営業
B8: 年間収入合計 | C8: ='1_ヒアリングシート'!C12+'1_ヒアリングシート'!C13 -> 8000000
B9: 税・社保 合計負担 | C9: ='2_所得税住民税'!C36 -> 1558922
B10: 手取り(年額) | C10: ='2_所得税住民税'!C37 -> 4441078
B12: iDeCo上限増額の年間節税額 | C12: ='3_iDeCo'!D14 -> 163200
B13: ふるさと納税 上限(概算) | C13: ='5_ふるさと納税'!C7 -> 78071
B14: 退職金 一時金手取り | C14: ='4_退職金'!C10 -> 14737500
